glocaltext/__init__.py
glocaltext/__main__.py
glocaltext/config.py
glocaltext/models.py
glocaltext/reporting.py
glocaltext/translate.py
glocaltext/workflow.py
glocaltext/translators/__init__.py
glocaltext/translators/base.py
glocaltext/translators/gemini_translator.py
glocaltext/translators/google_translator.py
glocaltext/translators/mock_translator.py
glocaltext-3.1.0.dist-info/licenses/LICENSE
glocaltext-3.1.0.dist-info/METADATA
glocaltext-3.1.0.dist-info/WHEEL
glocaltext-3.1.0.dist-info/entry_points.txt
glocaltext-3.1.0.dist-info/top_level.txt
glocaltext-3.1.0.dist-info/RECORD
