Metadata-Version: 2.4
Name: GlocalText
Version: 3.1.0
Summary: A config-driven script to batch translate files using various providers.
Author: OG-Open-Source
Project-URL: Homepage, https://github.com/OG-Open-Source/GlocalText
Project-URL: Repository, https://github.com/OG-Open-Source/GlocalText
Classifier: Programming Language :: Python :: 3
Classifier: Operating System :: OS Independent
Requires-Python: >=3.8
License-File: LICENSE
Requires-Dist: deep-translator
Requires-Dist: google-genai
Requires-Dist: PyYAML
Requires-Dist: regex
Dynamic: license-file
